odoo/addons/onaro/README.md
odoo/addons/onaro/__init__.py
odoo/addons/onaro/__manifest__.py
odoo/addons/onaro/controllers/__init__.py
odoo/addons/onaro/controllers/controllers.py
odoo/addons/onaro/data/base_automation.xml
odoo/addons/onaro/data/ir_default.xml
odoo/addons/onaro/data/product_attribute_value.xml
odoo/addons/onaro/data/product_product.xml
odoo/addons/onaro/data/product_template.xml
odoo/addons/onaro/data/product_template_attribute_line.xml
odoo/addons/onaro/demo/demo.xml
odoo/addons/onaro/listeners/__init__.py
odoo/addons/onaro/listeners/contract_listener.py
odoo/addons/onaro/migrations/12.0.0.1.0/post-migrate.py
odoo/addons/onaro/migrations/12.0.0.1.0/pre-migrate.py
odoo/addons/onaro/models/__init__.py
odoo/addons/onaro/models/crm_lead.py
odoo/addons/onaro/models/crm_lead_line.py
odoo/addons/onaro/security/res_users.xml
odoo/addons/onaro/services/__init__.py
odoo/addons/onaro/services/crm_lead_service.py
odoo/addons/onaro/services/helpdesk_ticket_service.py
odoo/addons/onaro/services/schemas.py
odoo/addons/onaro/tests/__init__.py
odoo/addons/onaro/tests/common.py
odoo/addons/onaro/tests/common_service.py
odoo/addons/onaro/tests/test_crm_lead_service.py
odoo/addons/onaro/tests/test_helpdesk_ticket_service.py
odoo/addons/onaro/views/crm_lead.xml
odoo12_addon_onaro-12.0.0.1.1.dist-info/METADATA
odoo12_addon_onaro-12.0.0.1.1.dist-info/WHEEL
odoo12_addon_onaro-12.0.0.1.1.dist-info/top_level.txt
odoo12_addon_onaro-12.0.0.1.1.dist-info/RECORD
