Metadata-Version: 2.1
Name: odoo12-addon-onaro
Version: 12.0.0.1.1
Summary: Odoo customizations for Onaro
Home-page: https://coopdevs.org
Author: Coopdevs Treball SCCL
License: AGPL-3
Platform: UNKNOWN
Classifier: Programming Language :: Python
Classifier: Framework :: Odoo
Classifier: Framework :: Odoo :: 12.0
Classifier: License :: OSI Approved :: GNU Affero General Public License v3
Requires-Python: >=3.5
Requires-Dist: odoo12-addon-auth-api-key (==12.0.2.1.0.99.dev2)
Requires-Dist: odoo12-addon-base-rest (==12.0.3.0.6)
Requires-Dist: odoo12-addon-crm-lead-product (==12.0.1.0.0.99.dev12)
Requires-Dist: odoo12-addon-helpdesk-mgmt
Requires-Dist: odoo12-addon-partner-firstname (==12.0.1.1.0.99.dev2)
Requires-Dist: odoo12-addon-remove-dup-acc-num-constraint (==12.0.1.0.1)
Requires-Dist: odoo12-addon-telecom (==12.0.0.1.0)
Requires-Dist: odoo (<12.1dev,>=12.0a)
Requires-Dist: pycastiphone-client (==0.1.0)
